{"web":{"auth_uri":"https://accounts.google.com/o/oauth2/auth","client_secret":"DXhy8R0smJiWaM-c7E2lH3Ra","token_uri":"https://accounts.google.com/o/oauth2/token","client_email":"868567712595-u0o5nhvdl1n5rneo6cei5sq0uojpbme2@developer.gserviceaccount.com","redirect_uris":["https://www.example.com/oauth2callback"],"client_x509_cert_url":"https://www.googleapis.com/robot/v1/metadata/x509/868567712595-u0o5nhvdl1n5rneo6cei5sq0uojpbme2@developer.gserviceaccount.com","client_id":"868567712595-u0o5nhvdl1n5rneo6cei5sq0uojpbme2.apps.googleusercontent.com","auth_provider_x509_cert_url":"https://www.googleapis.com/oauth2/v1/certs","javascript_origins":["https://www.example.com"]}}